<?xml version="1.0" encoding="UTF-8" standalone="yes"?><data><medicos><medico><id>1</id><name>Juan</name><rol>Admin</rol><clave_sistema>1</clave_sistema><especialidad>Cardiologia</especialidad></medico><medico><id>55</id><name>Carlos</name><rol></rol><clave_sistema></clave_sistema><especialidad>Odontologia</especialidad></medico></medicos><pacientes><paciente><id>118</id><name>Emmanuel</name><rol></rol><fechaNac>24/05/2003 </fechaNac><telefono> 70932878</telefono></paciente><paciente><id>119</id><name>Daniel</name><rol></rol><fechaNac> 01/11/2004</fechaNac><telefono>88214770</telefono></paciente><paciente><id>119190941</id><name>Anthony</name><rol></rol><fechaNac>31/10/2004 </fechaNac><telefono> 83315857</telefono></paciente><paciente><id>3</id><name>3</name><rol></rol><fechaNac> 3</fechaNac><telefono> 3</telefono></paciente><paciente><id>12</id><name>12</name><rol></rol><fechaNac>12 </fechaNac><telefono> 2</telefono></paciente></pacientes><farmaceutas><farmaceuta><id>44</id><name>Enrique</name><rol></rol><clave_sistema></clave_sistema></farmaceuta><farmaceuta><id>2</id><name>2</name><rol></rol><clave_sistema></clave_sistema></farmaceuta></farmaceutas><medicamentos><medicamento><codigo>101</codigo><nombre>Ibuprofeno</nombre><presentacion>500mg</presentacion></medicamento><medicamento><codigo>202</codigo><nombre>Acetaminofen</nombre><presentacion>100mg</presentacion></medicamento><medicamento><codigo>303</codigo><nombre>Vitaminas</nombre><presentacion>200mg</presentacion></medicamento></medicamentos><recetas><receta><medicamentos><medicamentoRecetado><medicamento><codigo>303</codigo><nombre>Vitaminas</nombre><presentacion>200mg</presentacion></medicamento><cantidad>3</cantidad><indicaciones>3</indicaciones><duracionDias>3</duracionDias></medicamentoRecetado></medicamentos><estado>Confeccionada</estado><fechaRetiro></fechaRetiro><paciente><id>119</id><name>Daniel</name><rol></rol><fechaNac> 01/11/2004</fechaNac><telefono>88214770</telefono></paciente></receta><receta><medicamentos><medicamentoRecetado><medicamento><codigo>303</codigo><nombre>Vitaminas</nombre><presentacion>200mg</presentacion></medicamento><cantidad>3</cantidad><indicaciones>3</indicaciones><duracionDias>3</duracionDias></medicamentoRecetado></medicamentos><estado>Confeccionada</estado><fechaRetiro></fechaRetiro><paciente><id>119</id><name>Daniel</name><rol></rol><fechaNac> 01/11/2004</fechaNac><telefono>88214770</telefono></paciente></receta><receta><medicamentos><medicamentoRecetado><medicamento><codigo>202</codigo><nombre>Acetaminofen</nombre><presentacion>100mg</presentacion></medicamento><cantidad>5</cantidad><indicaciones>2</indicaciones><duracionDias>5</duracionDias></medicamentoRecetado></medicamentos><estado>Confeccionada</estado><fechaRetiro>2025-12-31</fechaRetiro><paciente><id>118</id><name>Emmanuel</name><rol></rol><fechaNac>24/05/2003 </fechaNac><telefono> 70932878</telefono></paciente></receta><receta><medicamentos><medicamentoRecetado><medicamento><codigo>202</codigo><nombre>Acetaminofen</nombre><presentacion>100mg</presentacion></medicamento><cantidad>5</cantidad><indicaciones>2</indicaciones><duracionDias>5</duracionDias></medicamentoRecetado></medicamentos><estado>Confeccionada</estado><fechaRetiro>2025-12-31</fechaRetiro><paciente><id>118</id><name>Emmanuel</name><rol></rol><fechaNac>24/05/2003 </fechaNac><telefono> 70932878</telefono></paciente></receta><receta><medicamentos><medicamentoRecetado><medicamento><codigo>101</codigo><nombre>Ibuprofeno</nombre><presentacion>500mg</presentacion></medicamento><cantidad>1</cantidad><indicaciones>3</indicaciones><duracionDias>2</duracionDias></medicamentoRecetado></medicamentos><estado>Confeccionada</estado><fechaRetiro>2025-12-31</fechaRetiro><paciente><id>12</id><name>12</name><rol></rol><fechaNac>12 </fechaNac><telefono> 2</telefono></paciente></receta><receta><medicamentos><medicamentoRecetado><medicamento><codigo>101</codigo><nombre>Ibuprofeno</nombre><presentacion>500mg</presentacion></medicamento><cantidad>1</cantidad><indicaciones>3</indicaciones><duracionDias>2</duracionDias></medicamentoRecetado></medicamentos><estado>Confeccionada</estado><fechaRetiro>2025-12-31</fechaRetiro><paciente><id>12</id><name>12</name><rol></rol><fechaNac>12 </fechaNac><telefono> 2</telefono></paciente></receta></recetas></data>